orionac_ai/__init__.py
orionac_ai/client.py
orionac_ai-0.2.1.dist-info/METADATA
orionac_ai-0.2.1.dist-info/WHEEL
orionac_ai-0.2.1.dist-info/top_level.txt
orionac_ai-0.2.1.dist-info/RECORD
