Metadata-Version: 2.1
Name: orionac-ai
Version: 0.2.1
Summary: Python client for Orionac AI API
Home-page: https://github.com/RishiR123/orionac-ai
Author: Zakaria
Author-email: rishi@orionac.in
Classifier: Programming Language :: Python :: 3
Classifier: License :: OSI Approved :: MIT License
Classifier: Operating System :: OS Independent
Requires-Python: >=3.10
Requires-Dist: requests>=2.28
